joe_username/__init__.py
joe_username/__main__.py
joe_username/generate.py
joe_username-0.2.0.dist-info/LICENSE
joe_username-0.2.0.dist-info/METADATA
joe_username-0.2.0.dist-info/WHEEL
joe_username-0.2.0.dist-info/entry_points.txt
joe_username-0.2.0.dist-info/top_level.txt
joe_username-0.2.0.dist-info/RECORD
