Metadata-Version: 2.1
Name: joe-username
Version: 0.2.0
Summary: Generate a bunch if words Joe says
Home-page: https://github.com/shreyas44/joe-username
Author: Shreyas
Author-email: shreyas.sreenivasa@gmail.com
License: MIT
Platform: UNKNOWN
Classifier: Programming Language :: Python :: 3
Classifier: License :: OSI Approved :: MIT License
Classifier: Operating System :: OS Independent
Requires-Python: >3.6.0
